discordanalytics/__init__.py
discordanalytics/client.py
discordanalytics-3.6.0.dist-info/licenses/LICENSE
discordanalytics-3.6.0.dist-info/METADATA
discordanalytics-3.6.0.dist-info/WHEEL
discordanalytics-3.6.0.dist-info/top_level.txt
discordanalytics-3.6.0.dist-info/RECORD
