Metadata-Version: 2.4
Name: discordanalytics
Version: 3.6.0
Summary: A Python package for interacting with Discord Analytics API
Author-email: ValDesign <valdesign.dev@gmail.com>
License:                     GNU GENERAL PUBLIC LICENSE
Project-URL: homepage, https://github.com/DiscordAnalytics/python-package
Project-URL: issues, https://github.com/DiscordAnalytics/python-package/issues
Requires-Python: >=3.8
License-File: LICENSE
Dynamic: license-file
